getajob/__init__.py
getajob/abstractions/models.py
getajob/abstractions/repository.py
getajob/abstractions/vendor_client_factory.py
getajob/config/settings.py
getajob/contexts/__init__.py
getajob/contexts/admin/__init__.py
getajob/contexts/admin/dashboard/__init__.py
getajob/contexts/admin/dashboard/models.py
getajob/contexts/admin/dashboard/repository.py
getajob/contexts/admin/dashboard/unit_of_work.py
getajob/contexts/admin/jobs/models.py
getajob/contexts/admin/jobs/repository.py
getajob/contexts/admin/jobs/unit_of_work.py
getajob/contexts/admin/search/__init__.py
getajob/contexts/admin/search/models.py
getajob/contexts/admin/search/repository.py
getajob/contexts/admin/users/models.py
getajob/contexts/admin/users/repository.py
getajob/contexts/applications/__init__.py
getajob/contexts/applications/applicant_tracking/__init__.py
getajob/contexts/applications/applicant_tracking/models.py
getajob/contexts/applications/applicant_tracking/repository.py
getajob/contexts/applications/application_fit/__init__.py
getajob/contexts/applications/application_fit/repository.py
getajob/contexts/applications/async_service.py
getajob/contexts/applications/enumerations.py
getajob/contexts/applications/models.py
getajob/contexts/applications/repository.py
getajob/contexts/applications/unit_of_work.py
getajob/contexts/chat/__init__.py
getajob/contexts/chat/async_service.py
getajob/contexts/chat/message/__init__.py
getajob/contexts/chat/message/models.py
getajob/contexts/chat/message/repository.py
getajob/contexts/chat/models.py
getajob/contexts/chat/repository.py
getajob/contexts/chat/unit_of_work.py
getajob/contexts/companies/__init__.py
getajob/contexts/companies/applicant_tracking_settings/__init__.py
getajob/contexts/companies/applicant_tracking_settings/models.py
getajob/contexts/companies/applicant_tracking_settings/repository.py
getajob/contexts/companies/async_service.py
getajob/contexts/companies/audit/__init__.py
getajob/contexts/companies/audit/async_service.py
getajob-0.8.1.dist-info/LICENSE
getajob-0.8.1.dist-info/METADATA
getajob-0.8.1.dist-info/WHEEL
getajob-0.8.1.dist-info/RECORD
